pyramid_sampler/__init__.py
pyramid_sampler/_logging.py
pyramid_sampler/_version.py
pyramid_sampler/_version.pyi
pyramid_sampler/py.typed
pyramid_sampler/sampler.py
pyramid_sampler-0.1.0.dist-info/licenses/LICENSE
pyramid_sampler-0.1.0.dist-info/METADATA
pyramid_sampler-0.1.0.dist-info/WHEEL
pyramid_sampler-0.1.0.dist-info/top_level.txt
pyramid_sampler-0.1.0.dist-info/RECORD
