Metadata-Version: 2.4
Name: pyramid_sampler
Version: 0.1.0
Summary: simple tools for creating image pyramids
Author-email: Chris Havlin <chris.havlin@gmail.com>
License: BSD 3-Clause License
Project-URL: Homepage, https://github.com/data-exp-lab/pyramid_sampler
Project-URL: Bug Tracker, https://github.com/data-exp-lab/pyramid_sampler/issues
Project-URL: Discussions, https://github.com/data-exp-lab/pyramid_sampler/discussions
Project-URL: Changelog, https://github.com/data-exp-lab/pyramid_sampler/releases
Classifier: Development Status :: 1 - Planning
Classifier: Intended Audience :: Science/Research
Classifier: Intended Audience :: Developers
Classifier: License :: OSI Approved :: BSD License
Classifier: Operating System :: OS Independent
Classifier: Programming Language :: Python
Classifier: Programming Language :: Python :: 3
Classifier: Programming Language :: Python :: 3 :: Only
Classifier: Programming Language :: Python :: 3.10
Classifier: Programming Language :: Python :: 3.11
Classifier: Programming Language :: Python :: 3.12
Classifier: Topic :: Scientific/Engineering
Classifier: Typing :: Typed
Requires-Python: >=3.10
License-File: LICENSE
Requires-Dist: numba
Requires-Dist: dask[array,distributed]
Requires-Dist: numpy>=1.21.0
Requires-Dist: zarr
Provides-Extra: test
Requires-Dist: pytest>=6; extra == "test"
Requires-Dist: pytest-cov>=3; extra == "test"
Provides-Extra: dev
Requires-Dist: pytest>=6; extra == "dev"
Requires-Dist: pytest-cov>=3; extra == "dev"
Provides-Extra: docs
Requires-Dist: sphinx>=7.0; extra == "docs"
Requires-Dist: myst_parser>=0.13; extra == "docs"
Requires-Dist: sphinx_copybutton; extra == "docs"
Requires-Dist: sphinx_autodoc_typehints; extra == "docs"
Requires-Dist: furo>=2023.08.17; extra == "docs"
Provides-Extra: full
Requires-Dist: matplotlib; extra == "full"
Dynamic: license-file
